{"traceId":null,"success":true,"throwable":null,"errorCode":null,"content":{"idCursor":0,"data":[{"modifiedTime":1703900247000,"creator":"073105202321093148","modifierNick":null,"code":"TPROC--4IA668916HKCDJ2O9KPRFBWT069H3G08AJ6KL7","modifier":"073105202321093148","creatorName":"刘海涛","version":"16","creatorNick":null,"modifierDisplayName":"刘海涛","createTime":1703900183000,"name":"未命名流程表单1689578279446","alias":null,"modifierName":"刘海涛","processType":"2","isNewDesign":"false","id":22876266457,"creatorDisplayName":"刘海涛","status":"PUBLISHED"}],"entities":null,"currentPage":1,"totalCount":1},"errorMsg":null}